jarextract/__main__.py
jarextract/extract.py
jarextract-0.1.1.dist-info/METADATA
jarextract-0.1.1.dist-info/WHEEL
jarextract-0.1.1.dist-info/entry_points.txt
jarextract-0.1.1.dist-info/RECORD
