Metadata-Version: 2.1
Name: jarextract
Version: 0.1.1
Summary: Extracts JAR file from executable.
Author: Sergey Dudanov
Author-email: sergey.dudanov@gmail.com
Requires-Python: >=3.8,<4.0
Classifier: Programming Language :: Python :: 3
Classifier: Programming Language :: Python :: 3.8
Classifier: Programming Language :: Python :: 3.9
Classifier: Programming Language :: Python :: 3.10
Classifier: Programming Language :: Python :: 3.11
Classifier: Programming Language :: Python :: 3.12
